ddc_human/__init__.py
ddc_human/client.py
ddc_human/server.py
ddc_human-0.0.1.dist-info/METADATA
ddc_human-0.0.1.dist-info/WHEEL
ddc_human-0.0.1.dist-info/top_level.txt
ddc_human-0.0.1.dist-info/RECORD
