Metadata-Version: 2.1
Name: ddc-human
Version: 0.0.1
Summary: This is a package for  raspberry 
Home-page: https://github.com/NocoldBob/robot
Author: fastbiubiu
Author-email: fastbiubiu@163.com
License: UNKNOWN
Platform: UNKNOWN
Classifier: Programming Language :: Python :: 3
Classifier: License :: OSI Approved :: MIT License
Classifier: Operating System :: OS Independent
